{
  "publicPath": "/_nuxt/",
  "all": [
    "../server/index.spa.html",
    "02d3b46.js",
    "2275a96.js",
    "285ffae.js",
    "314eeca.js",
    "4161079.js",
    "4216001.js",
    "439548e.js",
    "518900c.js",
    "61997ad.js",
    "66897b9.js",
    "LICENSES",
    "b16ee8f.js",
    "b2a8867.js",
    "c08fb7d.js",
    "dddcd85.js",
    "e49abe2.js",
    "e73598e.js",
    "f4a1f15.js",
    "ff23f85.js",
    "img/QTTlogo.861d624.png"
  ],
  "initial": [
    "dddcd85.js",
    "b2a8867.js",
    "4161079.js",
    "2275a96.js"
  ],
  "async": [
    "02d3b46.js",
    "285ffae.js",
    "314eeca.js",
    "4216001.js",
    "439548e.js",
    "518900c.js",
    "61997ad.js",
    "66897b9.js",
    "b16ee8f.js",
    "c08fb7d.js",
    "e49abe2.js",
    "e73598e.js",
    "f4a1f15.js",
    "ff23f85.js"
  ],
  "modules": {
    "10144573": [
      5
    ],
    "10379341": [
      5
    ],
    "14435610": [
      5
    ],
    "18808620": [
      13
    ],
    "39016300": [
      5
    ],
    "41982101": [
      13
    ],
    "44679750": [
      13
    ],
    "45254795": [
      5
    ],
    "47341527": [
      5
    ],
    "53875892": [
      5
    ],
    "56449119": [
      5
    ],
    "61086140": [
      13
    ],
    "64857807": [
      13
    ],
    "66067126": [
      5
    ],
    "73553029": [
      5
    ],
    "80599730": [
      13
    ],
    "02e6bf6a": [
      5
    ],
    "1a0c88ec": [
      13
    ],
    "18664f71": [
      13
    ],
    "abbb13a6": [
      13
    ],
    "14b7c7e6": [
      13
    ],
    "67764dad": [
      13
    ],
    "21bcd3c4": [
      13
    ],
    "15fc2077": [
      13
    ],
    "52e6496e": [
      13
    ],
    "5c5dedba": [
      13
    ],
    "6897daeb": [
      13
    ],
    "afc1b13c": [
      2
    ],
    "3b5c129a": [
      13
    ],
    "a9f1a986": [
      13
    ],
    "1772ae55": [
      13
    ],
    "353ee869": [
      13
    ],
    "668a309c": [
      13
    ],
    "e5707e1a": [
      13
    ],
    "28ee4602": [
      13
    ],
    "2a7f95f4": [
      13
    ],
    "cfe033a4": [
      13
    ],
    "3c5b6847": [
      13
    ],
    "0ed389e2": [
      13
    ],
    "700b4888": [
      13
    ],
    "60bc21be": [
      13
    ],
    "2068872a": [
      13
    ],
    "bc2f73a0": [
      13
    ],
    "e1f2fae0": [
      13
    ],
    "4334b628": [
      5
    ],
    "292f8550": [
      5
    ],
    "95e9a966": [
      13
    ],
    "039bb54c": [
      13
    ],
    "a20c6d44": [
      5
    ],
    "5b8dba70": [
      5
    ],
    "73324e2b": [
      5
    ],
    "e24bcd34": [
      13
    ],
    "15c29969": [
      13
    ],
    "e18d0400": [
      13
    ],
    "2e54fb91": [
      13
    ],
    "524f34e9": [
      5
    ],
    "1a549f30": [
      13
    ],
    "93cb0944": [
      13
    ],
    "20520b6e": [
      13
    ],
    "5e541458": [
      13
    ],
    "bf75db98": [
      13
    ],
    "7a537be0": [
      13
    ],
    "3ed38782": [
      13
    ],
    "6caaf576": [
      13
    ],
    "dd4ed476": [
      13
    ],
    "36cae362": [
      13
    ],
    "180ff4b8": [
      13
    ],
    "6584bcbd": [
      5
    ],
    "0a7576a4": [
      13
    ],
    "0ebf52e5": [
      13
    ],
    "2eb0a3fb": [
      13
    ],
    "9254427a": [
      13
    ],
    "f979e0be": [
      2
    ],
    "1f5ce1d2": [
      2
    ],
    "7e8c385b": [
      2
    ],
    "bd4ea550": [
      2
    ],
    "3e0cabec": [
      2
    ],
    "142eb312": [
      2
    ],
    "3a2fdd9c": [
      2
    ],
    "59342e5a": [
      2
    ],
    "0364eaac": [
      2
    ],
    "5e4ad97d": [
      2
    ],
    "006be5af": [
      2
    ],
    "33a86ef7": [
      2
    ],
    "4cda43e1": [
      2
    ],
    "2439b48c": [
      2
    ],
    "0484ae02": [
      2
    ],
    "bc92e6a2": [
      2
    ],
    "5e53369f": [
      2
    ],
    "6d4d2d8e": [
      2
    ],
    "0191122d": [
      2
    ],
    "22d4c334": [
      2
    ],
    "5adc4185": [
      2
    ],
    "0439440e": [
      2
    ],
    "a4ab0fb0": [
      13
    ],
    "2652ce21": [
      13
    ],
    "727bf9fe": [
      13
    ],
    "1d62927f": [
      13
    ],
    "4df69b98": [
      13
    ],
    "6d7d5ce7": [
      13
    ],
    "6d9dd5d4": [
      13
    ],
    "e131b9e4": [
      13
    ],
    "53740c45": [
      13
    ],
    "5b84ce68": [
      13
    ],
    "4cd2df05": [
      13
    ],
    "6ffc805d": [
      13
    ],
    "058af96e": [
      13
    ],
    "588957c4": [
      13
    ],
    "1db48ecc": [
      13
    ],
    "794ab49a": [
      13
    ],
    "08dd6e57": [
      13
    ],
    "7b8796ee": [
      13
    ],
    "72822f5b": [
      13
    ],
    "effe5974": [
      13
    ],
    "36dcfbae": [
      13
    ],
    "3f737e84": [
      13
    ],
    "4da1cb49": [
      13
    ],
    "0a893163": [
      5
    ],
    "c5b81ba2": [
      5
    ],
    "e22a4d82": [
      5
    ],
    "1bc469ca": [
      13
    ],
    "3aaea6ad": [
      13
    ],
    "14dce358": [
      13
    ],
    "64992bd7": [
      13
    ],
    "0de9d06f": [
      13
    ],
    "989c7390": [
      13
    ],
    "8fea22fe": [
      13
    ],
    "e4eca3c0": [
      13
    ],
    "3e9fa02c": [
      13
    ],
    "ae9cd01e": [
      13
    ],
    "31ce6fea": [
      13
    ],
    "a1793266": [
      13
    ],
    "6a5c052c": [
      13
    ],
    "541918c6": [
      13
    ],
    "406941d6": [
      13
    ],
    "932342e2": [
      13
    ],
    "e35f2530": [
      13
    ],
    "4852411e": [
      5
    ],
    "a7e26c16": [
      5
    ],
    "6fbaffea": [
      13
    ],
    "1e509214": [
      13
    ],
    "016be5ac": [
      5
    ],
    "febb8a94": [
      5
    ],
    "04b75458": [
      13
    ],
    "4be4f9a5": [
      5
    ],
    "137ffe39": [
      5
    ],
    "88cf4ae8": [
      5
    ],
    "5ee0db8e": [
      13
    ],
    "0fd0e5a4": [
      13
    ],
    "3be5da94": [
      13
    ],
    "86d53902": [
      13
    ],
    "4ba45adc": [
      13
    ],
    "f22026aa": [
      13
    ],
    "67762a70": [
      13
    ],
    "68ef9d73": [
      13
    ],
    "993c8d2e": [
      13
    ],
    "46a7b030": [
      13
    ],
    "5f0c0e86": [
      13
    ],
    "45f2a448": [
      13
    ],
    "b7a9f24c": [
      13
    ],
    "784e0cd9": [
      13
    ],
    "0544d2c5": [
      13
    ],
    "9f487d34": [
      5
    ],
    "04be12fe": [
      5
    ],
    "3d9fcee8": [
      5
    ],
    "c56bcb50": [
      2
    ],
    "7d750749": [
      13
    ],
    "6420c5ed": [
      13
    ],
    "0df4c610": [
      13
    ],
    "19e6c506": [
      13
    ],
    "71fef15c": [
      13
    ],
    "15aad436": [
      13
    ],
    "8d71e5c6": [
      13
    ],
    "cd2a740c": [
      13
    ],
    "51e7507a": [
      13
    ],
    "793b0a3e": [
      13
    ],
    "26098e44": [
      13
    ],
    "2bac323b": [
      13
    ],
    "d8d997b0": [
      13
    ],
    "378fc934": [
      13
    ],
    "094cc8a5": [
      13
    ],
    "6ecf5774": [
      13
    ],
    "44a5f43b": [
      13
    ],
    "17026ece": [
      13
    ],
    "2f99f2cb": [
      13
    ],
    "4234dde0": [
      13
    ],
    "0bef6943": [
      13
    ],
    "04d4a195": [
      13
    ],
    "1547f9ca": [
      13
    ],
    "7f35a404": [
      13
    ],
    "7690054b": [
      13
    ],
    "2e6712a9": [
      13
    ],
    "4b418ce4": [
      5
    ],
    "0ddc3a06": [
      13
    ],
    "ebc9e31a": [
      13
    ],
    "52a5ab40": [
      13
    ],
    "2b218c87": [
      13
    ],
    "5ebec88a": [
      13
    ],
    "4eef4ce9": [
      2
    ],
    "6183bc54": [
      5
    ],
    "2dddfa91": [
      5
    ],
    "283fac9f": [
      13
    ],
    "6c29a8ea": [
      13
    ],
    "0ac7c50b": [
      13
    ],
    "3ab55f48": [
      13
    ],
    "4acddb77": [
      13
    ],
    "7feb271c": [
      13
    ],
    "49b2c2d1": [
      13
    ],
    "065b9b64": [
      13
    ],
    "72d2d892": [
      13
    ],
    "01f82100": [
      13
    ],
    "189128a6": [
      13
    ],
    "7369f536": [
      13
    ],
    "2875fc48": [
      13
    ],
    "39c57994": [
      13
    ],
    "84e0c714": [
      13
    ],
    "0a0f0f60": [
      13
    ],
    "e9118afa": [
      13
    ],
    "43512ce2": [
      13
    ],
    "503b95fa": [
      13
    ],
    "44bc41d0": [
      13
    ],
    "6ff60934": [
      13
    ],
    "6f085544": [
      13
    ],
    "8e06490c": [
      13
    ],
    "b588eefe": [
      13
    ],
    "d70f750c": [
      13
    ],
    "73838e4c": [
      13
    ],
    "35930b15": [
      13
    ],
    "ebde6618": [
      13
    ],
    "450ff055": [
      13
    ],
    "f25acece": [
      13
    ],
    "2c8c41a6": [
      13
    ],
    "623ce554": [
      13
    ],
    "70609d08": [
      13
    ],
    "1c6b02be": [
      13
    ],
    "11460b2e": [
      13
    ],
    "2c23fbfa": [
      13
    ],
    "32bd8982": [
      13
    ],
    "0b117d0e": [
      13
    ],
    "6cd5acd6": [
      13
    ],
    "fba04f9c": [
      13
    ],
    "0648f013": [
      13
    ],
    "6e6ea598": [
      13
    ],
    "542a2c96": [
      13
    ],
    "7e7a5d66": [
      13
    ],
    "a9c85fe6": [
      13
    ],
    "62dc96d7": [
      2
    ],
    "468f1c5c": [
      2
    ],
    "36e76db1": [
      5
    ],
    "10283a45": [
      5
    ],
    "3f725b4b": [
      5
    ],
    "4456b5a8": [
      5
    ],
    "1eebe40c": [
      5
    ],
    "69848d6a": [
      13
    ],
    "b12729ea": [
      13
    ],
    "5d06929b": [
      13
    ],
    "762214b1": [
      13
    ],
    "75b40879": [
      13
    ],
    "5d217993": [
      13
    ],
    "780d10b9": [
      13
    ],
    "781896ce": [
      13
    ],
    "539742b5": [
      13
    ],
    "6535f62c": [
      13
    ],
    "1bfc2d63": [
      13
    ],
    "e839cd84": [
      13
    ],
    "3c70428a": [
      13
    ],
    "35adfea5": [
      13
    ],
    "a46094a0": [
      5
    ],
    "a76901a6": [
      13
    ],
    "5459ef04": [
      5
    ],
    "0e352fbb": [
      5
    ],
    "2df7d903": [
      5
    ],
    "1e83fec3": [
      5
    ],
    "426dd9ec": [
      2
    ],
    "75d8a873": [
      5
    ],
    "00c854f0": [
      5
    ],
    "4afc0170": [
      5
    ],
    "19ce9f5a": [
      5
    ],
    "ccf755c6": [
      5
    ],
    "18acb0d3": [
      5
    ],
    "22e46731": [
      5
    ],
    "691175a6": [
      5
    ],
    "068f404e": [
      5
    ],
    "606002da": [
      5
    ],
    "5ff04213": [
      5
    ],
    "3b3b101a": [
      5
    ],
    "2fdccb50": [
      5
    ],
    "11af9b76": [
      5
    ],
    "7dede2b6": [
      5
    ],
    "1f71e4fb": [
      5
    ],
    "330defb3": [
      5
    ],
    "64f9d7e6": [
      5
    ],
    "a2202cd2": [
      5
    ],
    "dae0d75a": [
      5
    ],
    "c92ab236": [
      5
    ],
    "46f2b45a": [
      5
    ],
    "4af32eae": [
      5
    ],
    "760fcb13": [
      5
    ],
    "178e1dea": [
      5
    ],
    "256935a8": [
      5
    ],
    "43ad53d6": [
      5
    ],
    "41e162ec": [
      5
    ],
    "0b37173e": [
      5
    ],
    "3ee7c2da": [
      5
    ],
    "a80f54a6": [
      5
    ],
    "051c1ac6": [
      5
    ],
    "85aeae5a": [
      5
    ],
    "305baaf9": [
      5
    ],
    "2c4e2b40": [
      5
    ],
    "a7fdb760": [
      5
    ],
    "2bceb0fe": [
      5
    ],
    "99e4c7be": [
      5
    ],
    "21a0fd0e": [
      5
    ],
    "a849465a": [
      5
    ],
    "683f38a2": [
      5
    ],
    "74df5129": [
      5
    ],
    "09c51233": [
      5
    ],
    "6edd6f25": [
      5
    ],
    "0877bea3": [
      5
    ],
    "716c5508": [
      5
    ],
    "ea05dc9a": [
      5
    ],
    "69a802fb": [
      5
    ],
    "f93bcb18": [
      5
    ],
    "15524f81": [
      5
    ],
    "bee52832": [
      5
    ],
    "347c2f5a": [
      5
    ],
    "79b770ac": [
      5
    ],
    "d1fa6abe": [
      5
    ],
    "b93045fe": [
      5
    ],
    "009c34d0": [
      5
    ],
    "4c57b4d9": [
      5
    ],
    "24356c40": [
      5
    ],
    "acb1b6f4": [
      5
    ],
    "d649cffe": [
      5
    ],
    "034fb153": [
      5
    ],
    "02290cd0": [
      5
    ],
    "0f64bc0c": [
      5
    ],
    "85f6cb76": [
      5
    ],
    "2d2a049a": [
      5
    ],
    "48d481da": [
      5
    ],
    "0a966dfe": [
      5
    ],
    "6fe5f1cd": [
      5
    ],
    "47b787e5": [
      5
    ],
    "7ade8301": [
      5
    ],
    "7f5e7834": [
      5
    ],
    "6df2a17e": [
      5
    ],
    "87b37098": [
      5
    ],
    "1b31b3b1": [
      5
    ],
    "d2046cda": [
      5
    ],
    "07b79d13": [
      5
    ],
    "53fabb1a": [
      5
    ],
    "2b82ffb0": [
      5
    ],
    "e33dfb3e": [
      5
    ],
    "bc3029d2": [
      5
    ],
    "9d2ff002": [
      5
    ],
    "25effe1a": [
      5
    ],
    "4f5a50ea": [
      5
    ],
    "aa503e4e": [
      5
    ],
    "5f384701": [
      5
    ],
    "3d62d874": [
      5
    ],
    "a4a7e6de": [
      5
    ],
    "4fdbcefc": [
      5
    ],
    "48f4eb98": [
      5
    ],
    "d56b8ff2": [
      5
    ],
    "055fac92": [
      5
    ],
    "6e9f7c45": [
      5
    ],
    "37ef4c36": [
      5
    ],
    "469a26b3": [
      5
    ],
    "18aa4083": [
      5
    ],
    "49ee9335": [
      5
    ],
    "7be47804": [
      5
    ],
    "0611e6c1": [
      5
    ],
    "a1799500": [
      5
    ],
    "fcf8e018": [
      5
    ],
    "2f74f99c": [
      5
    ],
    "2fb4e193": [
      5
    ],
    "6eeb9dbd": [
      5
    ],
    "3de7a990": [
      5
    ],
    "098f1fb3": [
      5
    ],
    "4efc56cd": [
      5
    ],
    "34cf6517": [
      5
    ],
    "455a0c9f": [
      5
    ],
    "2c719862": [
      5
    ],
    "4c610dd3": [
      5
    ],
    "49fc9adb": [
      5
    ],
    "8c1cec0e": [
      5
    ],
    "85508d90": [
      5
    ],
    "33f0c27c": [
      5
    ],
    "08bfcf43": [
      5
    ],
    "4272eb31": [
      5
    ],
    "01b6f283": [
      5
    ],
    "78cf4d45": [
      5
    ],
    "6e45ceec": [
      5
    ],
    "4eec4585": [
      5
    ],
    "309a6269": [
      5
    ],
    "5df52a0f": [
      5
    ],
    "ebd2b1d0": [
      5
    ],
    "45f70c72": [
      5
    ],
    "5cdd5994": [
      5
    ],
    "181aa05a": [
      5
    ],
    "29c66c3d": [
      5
    ],
    "4d13a98c": [
      5
    ],
    "3f118e79": [
      5
    ],
    "4fc2b4ce": [
      5
    ],
    "1bf6896b": [
      5
    ],
    "696adea9": [
      5
    ],
    "5014a013": [
      5
    ],
    "21416a2f": [
      5
    ],
    "2ea4d05a": [
      5
    ],
    "4d33d619": [
      5
    ],
    "478ab345": [
      5
    ],
    "761a6181": [
      5
    ],
    "5a866fd3": [
      5
    ],
    "a047e274": [
      5
    ],
    "9d06d818": [
      5
    ],
    "3d8055ad": [
      5
    ],
    "a78e7b9a": [
      5
    ],
    "06f286fc": [
      5
    ],
    "872f1f5a": [
      5
    ],
    "6616451d": [
      5
    ],
    "00d9439a": [
      5
    ],
    "6daf6278": [
      5
    ],
    "ed848158": [
      5
    ],
    "5dcef956": [
      5
    ],
    "127a1006": [
      5
    ],
    "100de841": [
      5
    ],
    "100fb9bd": [
      5
    ],
    "1b65bedb": [
      5
    ],
    "06f30322": [
      5
    ],
    "c2a36778": [
      5
    ],
    "5e0b7a00": [
      5
    ],
    "389a42eb": [
      5
    ],
    "48a54dd2": [
      5
    ],
    "2910c6a6": [
      5
    ],
    "1b159648": [
      5
    ],
    "56ece300": [
      5
    ],
    "2dcf5c13": [
      5
    ],
    "3305b4a8": [
      5
    ],
    "7035366a": [
      5
    ],
    "0f420e5c": [
      5
    ],
    "38cb71f0": [
      5
    ],
    "45d9933d": [
      5
    ],
    "36733bf6": [
      5
    ],
    "c2bd069c": [
      5
    ],
    "2bf6c197": [
      5
    ],
    "374d71b0": [
      5
    ],
    "340c6754": [
      5
    ],
    "79eb9c9d": [
      5
    ],
    "5bfdf88f": [
      5
    ],
    "2d89d63e": [
      5
    ],
    "68ffaa82": [
      5
    ],
    "6aa21a5c": [
      5
    ],
    "056198ce": [
      5
    ],
    "3d57ed22": [
      5
    ],
    "412ed8b6": [
      5
    ],
    "153eb94e": [
      5
    ],
    "0945996a": [
      5
    ],
    "6a66d703": [
      5
    ],
    "ff923408": [
      5
    ],
    "2c1b6c9f": [
      5
    ],
    "90aaa03c": [
      5
    ],
    "3422c500": [
      5
    ],
    "32e849b8": [
      5
    ],
    "2c143a07": [
      5
    ],
    "554aa6bf": [
      5
    ],
    "2520d906": [
      5
    ],
    "7438d2a3": [
      5
    ],
    "2ce944fc": [
      5
    ],
    "37fc42c6": [
      5
    ],
    "8109f452": [
      5
    ],
    "31867f56": [
      5
    ],
    "799ca68d": [
      5
    ],
    "2c4d008e": [
      5
    ],
    "7ed82876": [
      5
    ],
    "54f1e9bc": [
      5
    ],
    "5d427940": [
      5
    ],
    "30b5e9f2": [
      5
    ],
    "08dc3080": [
      5
    ],
    "197077bd": [
      5
    ],
    "f25baef6": [
      5
    ],
    "0e213ab8": [
      5
    ],
    "22036df6": [
      5
    ],
    "e21ef756": [
      5
    ],
    "2db410b9": [
      5
    ],
    "deb6c2f4": [
      5
    ],
    "3e31bd3a": [
      5
    ],
    "408d42aa": [
      5
    ],
    "57e71251": [
      5
    ],
    "20eb4ef1": [
      5
    ],
    "972334d8": [
      5
    ],
    "398f8673": [
      5
    ],
    "a8459a98": [
      5
    ],
    "7aded5a4": [
      5
    ],
    "45e9fb90": [
      5
    ],
    "3d1667a4": [
      5
    ],
    "7092f780": [
      5
    ],
    "755d152b": [
      5
    ],
    "6e8aaf5c": [
      5
    ],
    "2e6b8d42": [
      5
    ],
    "737dcf68": [
      5
    ],
    "28f422bf": [
      5
    ],
    "2b1c1433": [
      5
    ],
    "6b9b42ec": [
      5
    ],
    "146ca0f4": [
      5
    ],
    "8892c2c6": [
      5
    ],
    "6c4a3732": [
      5
    ],
    "6d98f259": [
      5
    ],
    "57f35489": [
      5
    ],
    "7ac3c01a": [
      5
    ],
    "d9eb8824": [
      5
    ],
    "b705a208": [
      5
    ],
    "73e03e4e": [
      5
    ],
    "66e1f153": [
      5
    ],
    "7de5a2d0": [
      5
    ],
    "f41e6046": [
      5
    ],
    "d602db90": [
      5
    ],
    "11ee1a6a": [
      5
    ],
    "7de82b2a": [
      5
    ],
    "5811fa18": [
      5
    ],
    "8670cbba": [
      5
    ],
    "7913e753": [
      5
    ],
    "6efbf787": [
      5
    ],
    "2485765f": [
      5
    ],
    "11bef3e4": [
      5
    ],
    "2e03d7c8": [
      5
    ],
    "54095d3e": [
      5
    ],
    "d21d9776": [
      5
    ],
    "15ec9385": [
      5
    ],
    "03cc1716": [
      5
    ],
    "2308c254": [
      5
    ],
    "4750fa54": [
      5
    ],
    "6c7e7496": [
      5
    ],
    "883f62cc": [
      5
    ],
    "6144896f": [
      5
    ],
    "0cf457da": [
      5
    ],
    "2c452256": [
      5
    ],
    "0fa90e80": [
      5
    ],
    "d2a3d998": [
      5
    ],
    "9e022986": [
      5
    ],
    "2aad3d20": [
      5
    ],
    "2832f388": [
      5
    ],
    "6ae847b9": [
      5
    ],
    "c1c49b28": [
      5
    ],
    "7186ceac": [
      5
    ],
    "c9237b44": [
      5
    ],
    "194498a8": [
      5
    ],
    "7404299e": [
      5
    ],
    "2ccbfea9": [
      5
    ],
    "425893da": [
      5
    ],
    "3c63e0a0": [
      5
    ],
    "4f0a6dfc": [
      5
    ],
    "1be56682": [
      5
    ],
    "46c87944": [
      5
    ],
    "026f32fb": [
      5
    ],
    "b72dcc52": [
      5
    ],
    "49c5b4bd": [
      5
    ],
    "dc51b60c": [
      5
    ],
    "30e1cdfa": [
      5
    ],
    "1a9767e4": [
      5
    ],
    "447bc5b0": [
      5
    ],
    "46fdd3ec": [
      5
    ],
    "592f187e": [
      5
    ],
    "004a32c4": [
      5
    ],
    "690d3262": [
      5
    ],
    "306e09bc": [
      5
    ],
    "814996b8": [
      5
    ],
    "4cc852d0": [
      5
    ],
    "019add7e": [
      5
    ],
    "2e09b0d8": [
      5
    ],
    "0c7a8e96": [
      5
    ],
    "e9da77e6": [
      5
    ],
    "094b317d": [
      5
    ],
    "6c5f81e3": [
      5
    ],
    "b147243e": [
      5
    ],
    "c395c242": [
      5
    ],
    "72e76da5": [
      5
    ],
    "96309c0c": [
      5
    ],
    "4c330d62": [
      5
    ],
    "19ff7776": [
      5
    ],
    "03164764": [
      5
    ],
    "3fa77dee": [
      13
    ],
    "7cdd336a": [
      2
    ],
    "18c68c3d": [
      5
    ],
    "b859c3e0": [
      2
    ],
    "ffec7ea2": [
      13
    ],
    "e26d839c": [
      13
    ],
    "37c041d0": [
      13
    ],
    "1602e3c1": [
      13
    ],
    "324df2fc": [
      13
    ],
    "ca30424c": [
      13
    ],
    "7e27da4c": [
      13
    ],
    "5f23b6ad": [
      13
    ],
    "3ee6078c": [
      13
    ],
    "49639eaa": [
      13
    ],
    "6f64e54e": [
      13
    ],
    "4d4e68ce": [
      13
    ],
    "7ea31820": [
      13
    ],
    "c49781a6": [
      13
    ],
    "b92b2556": [
      13
    ],
    "e6ca546e": [
      13
    ],
    "ceb4f634": [
      13
    ],
    "57dc478e": [
      13
    ],
    "004ad760": [
      13
    ],
    "4c8fb000": [
      13
    ],
    "64aa95c4": [
      13
    ],
    "2c1a83df": [
      13
    ],
    "58e56a7c": [
      13
    ],
    "0e39f8fa": [
      13
    ],
    "7c5e686c": [
      13
    ],
    "523116d2": [
      13
    ],
    "09281b5c": [
      13
    ],
    "f751791c": [
      13
    ],
    "6ff21cc0": [
      13
    ],
    "630f566a": [
      13
    ],
    "03888306": [
      13
    ],
    "d2d4f434": [
      13
    ],
    "3e3f17a2": [
      13
    ],
    "b636e606": [
      13
    ],
    "e597334c": [
      13
    ],
    "7ae08c8b": [
      13
    ],
    "a7abf2ce": [
      13
    ],
    "34f95710": [
      13
    ],
    "020e3df0": [
      13
    ],
    "6839d2e8": [
      13
    ],
    "32e0f50b": [
      13
    ],
    "44a57c7f": [
      13
    ],
    "93264c74": [
      13
    ],
    "baa1e11c": [
      13
    ],
    "43b3c1cf": [
      2
    ],
    "16bc524d": [
      2
    ],
    "371e826c": [
      2
    ],
    "179727c8": [
      2
    ],
    "07660e14": [
      5
    ],
    "447f44f9": [
      5
    ],
    "de327722": [
      5
    ],
    "751ee080": [
      2
    ],
    "149c93ea": [
      5
    ],
    "00995af2": [
      5
    ],
    "08da60c2": [
      5
    ],
    "c40ab6bc": [
      5
    ],
    "0c515e6d": [
      5
    ],
    "3f472c0a": [
      5
    ],
    "415091af": [
      5
    ],
    "7db56fdd": [
      5
    ],
    "37d6568e": [
      5
    ],
    "08fc1a75": [
      5
    ],
    "4ac26890": [
      5
    ],
    "04600418": [
      5
    ],
    "ea34adca": [
      5
    ],
    "75eff8aa": [
      5
    ],
    "4fc60c4c": [
      5
    ],
    "be591d06": [
      13
    ],
    "e30410ac": [
      13
    ],
    "49a35730": [
      13
    ],
    "297609af": [
      13
    ],
    "c814d6da": [
      13
    ],
    "097a69f0": [
      13
    ],
    "1ffc1d37": [
      13
    ],
    "18827a8a": [
      13
    ],
    "43570a4e": [
      13
    ],
    "46b6ab1e": [
      13
    ],
    "46e1b8d7": [
      13
    ],
    "fbb9a212": [
      13
    ],
    "067c8b48": [
      13
    ],
    "6bd7c5be": [
      13
    ],
    "99a38e5e": [
      13
    ],
    "7901f42b": [
      13
    ],
    "2dd25d54": [
      13
    ],
    "45f5427c": [
      13
    ],
    "026c8cd5": [
      13
    ],
    "4d627174": [
      13
    ],
    "9534ef5a": [
      13
    ],
    "1a42e7b9": [
      13
    ],
    "5c833eae": [
      13
    ],
    "18b1b970": [
      13
    ],
    "5496452a": [
      13
    ],
    "35b3e775": [
      13
    ],
    "0d25bcc3": [
      13
    ],
    "9190dbf2": [
      13
    ],
    "23844e74": [
      13
    ],
    "073a8883": [
      13
    ],
    "42f76d90": [
      13
    ],
    "1da54fe3": [
      13
    ],
    "3d9db17a": [
      13
    ],
    "1930e7d9": [
      9
    ],
    "962e68dc": [
      8,
      9
    ],
    "6fbddb54": [
      16,
      9,
      8
    ],
    "51696bd3": [
      18,
      20
    ],
    "448fd837": [
      8,
      9
    ],
    "c88f4f58": [
      8,
      9
    ],
    "0a3f8fe2": [
      8,
      9
    ],
    "07d35bfc": [
      8,
      9
    ],
    "a9ec0d8c": [
      8,
      9
    ],
    "cf17e5d8": [
      9
    ],
    "3ffaa052": [
      9
    ],
    "187b843d": [
      9
    ],
    "09ffb52f": [
      9
    ],
    "28f531e5": [
      9
    ],
    "3597a3e1": [
      9
    ],
    "096d8523": [
      9
    ],
    "66aeaa8a": [
      8,
      9
    ],
    "a4c4eff0": [
      8,
      9
    ],
    "390c1368": [
      16,
      9,
      8
    ],
    "3eff42ca": [
      16,
      9,
      8
    ],
    "139b7b04": [
      18,
      20
    ],
    "5921b8cb": [
      18,
      20
    ],
    "e76fbc6e": [
      18,
      20
    ],
    "e6bf6500": [
      18,
      20
    ],
    "4ac6c94e": [
      18,
      20
    ],
    "59f701b9": [
      18,
      20
    ],
    "05b41901": [
      18,
      20
    ],
    "1c6715de": [
      18,
      20
    ],
    "1fee7bb9": [
      16,
      9,
      8
    ],
    "503a3fd2": [
      16,
      9,
      8
    ],
    "7a3d1ca0": [
      16,
      9,
      8
    ],
    "b30d510c": [
      16,
      9,
      8
    ],
    "2ea1f1f8": [
      16,
      9,
      8
    ],
    "e172e826": [
      1
    ],
    "421a4900": [
      1
    ],
    "2c8a3028": [
      1
    ],
    "9f48d5b0": [
      1
    ],
    "fcdf4978": [
      1
    ]
  },
  "assetsMapping": {
    "23682a6b": [
      "02d3b46.js"
    ],
    "1a3ae26b": [
      "2275a96.js"
    ],
    "88d90b60": [
      "285ffae.js"
    ],
    "05f51b1b": [
      "314eeca.js"
    ],
    "7ea24c87": [
      "4161079.js"
    ],
    "bb1b2030": [
      "4216001.js"
    ],
    "eed86448": [
      "439548e.js"
    ],
    "88cc4d96": [
      "518900c.js"
    ],
    "636bab65": [
      "61997ad.js"
    ],
    "1eac8c23": [
      "66897b9.js"
    ],
    "1ec7c360": [
      "b16ee8f.js"
    ],
    "085a35c4": [
      "b2a8867.js"
    ],
    "919621b4": [
      "c08fb7d.js"
    ],
    "6fca0322": [
      "dddcd85.js"
    ],
    "2a130dde": [
      "e49abe2.js"
    ],
    "7d8e1504": [
      "e73598e.js"
    ],
    "252fad7e": [
      "f4a1f15.js"
    ],
    "3e064611": [
      "ff23f85.js"
    ]
  }
}